setup.py
lastpass_cloudbleed/__init__.py
lastpass_cloudbleed.egg-info/PKG-INFO
lastpass_cloudbleed.egg-info/SOURCES.txt
lastpass_cloudbleed.egg-info/dependency_links.txt
lastpass_cloudbleed.egg-info/entry_points.txt
lastpass_cloudbleed.egg-info/requires.txt
lastpass_cloudbleed.egg-info/top_level.txt