Metadata-Version: 1.0
Name: lastpass-cloudbleed
Version: 1.0
Summary: Compares the publicly available CloudFlare domains list to your LastPass vault, listing potentially compromised domains in your vault.
Home-page: https://github.com/angstwad/lastpass-cloudbleed
Author: Paul Durivage
Author-email: pauldurivage@gmail.com
License: Apache 2.0
Platform: UNKNOWN
